README.txt
setup.py
mmis/Clock.py
mmis/CryoHeater.py
mmis/DebugFunctions.py
mmis/DualHeater.py
mmis/DualHeater_default.py
mmis/Functions.py
mmis/GUI.py
mmis/LiqN2Control.py
mmis/RealTimeClock.py
mmis/SampleHeater.py
mmis/Softwareupdate.py
mmis/__init__.py
mmis/startup.py
mmis.egg-info/PKG-INFO
mmis.egg-info/SOURCES.txt
mmis.egg-info/dependency_links.txt
mmis.egg-info/requires.txt
mmis.egg-info/top_level.txt
mmis/Images/Connected.png
mmis/Images/DEMOico.ico
mmis/Images/Disconnected.png
mmis/Images/HZlogo.png
mmis/Images/Logo.png
mmis/Images/MMIstart.png
mmis/Images/Thumbs.db
mmis/Images/graph.png
mmis/Images/liquid-nitrogen.png
mmis/Images/warning.png