Metadata-Version: 1.0
Name: mmis
Version: 1.36
Summary: control software for the Modular Microscope Instrument
Home-page: UNKNOWN
Author: Rajeev Bheemireddy TUDelft-DEMO
Author-email: UNKNOWN
License: UNKNOWN
Platform: UNKNOWN
